HA_D.v

// Author: Ha How Ung
// Written on: 8 April 2021 (Fri)
// Title: Dataflow modelling of a half-adder

module HA_D (a, b, s, c);

	input a, b;
	output s, c;

	assign s = a ^ b;
	assign c = a & b;
	
endmodule

FA_S.v

// Author: Ha How Ung
// Written on: 8 April 2021 (Fri)
// Title: Structural modelling of full-adder

module FA_S (Cin, A, B, Sum, Cout) ;

	input Cin, A, B;
	output Sum, Cout ;
	wire s1, s2, s3;
	
	HA_D u1 (A, B, s1, s2);
	HA_D u2 (s1, Cin, Sum, s3);
	assign Cout = s2 | s3;
	
endmodule

RCA4.v

// Author: Ha How Ung
// Written on: 8 April 2021 (Fri)
// Title: 4-bit ripple-carry adder

module RCA4 (
	input [3:0] A, B, 
	input Cin,
	output [3:0] S, 
	output Cout
);

	wire c1, c2, c3;
	
	FA_S u0 (.Cin(Cin), .A(A[0]), .B(B[0]), .Sum(S[0]), .Cout(c1));
	FA_S u1 (.Cin(c1), .A(A[1]), .B(B[1]), .Sum(S[1]), .Cout(c2));
	FA_S u2 (.Cin(c2), .A(A[2]), .B(B[2]), .Sum(S[2]), .Cout(c3));
	FA_S u3 (.Cin(c3), .A(A[3]), .B(B[3]), .Sum(S[3]), .Cout(Cout));

endmodule

RCA8.v

// Author: Ha How Ung
// Written on: 8 April 2021 (Fri)
// Title: 8-bit adder/subtractor unit

module RCA8 (
	input [7:0] a, b,
	input sub,
	output [8:0] z
);

	wire c;
	
	RCA4 u0 (.A(a[3:0]), .B(b[3:0] ^ (sub ? 8'hF : 8'h0)), .Cin(sub), .S(z[3:0]), .Cout(c));
	RCA4 u1 (.A(a[7:4]), .B(b[7:4] ^ (sub ? 8'hF : 8'h0)), .Cin(c), .S(z[7:4]), .Cout(z[8]));

endmodule

RCA8_testbench.v
`timescale 10ns/1ns

module RCA8_testbench(); // no input, no output
  
  reg [7:0] a, b;   // always declare inputs as reg
  reg sub;
  wire [7:0] z;    
  wire Cout;	    // and outputs as wire
  
  RCA8 DUT ( .a(a), .b(b), .sub(sub), .z(z), .Cout(Cout));
  
  initial
  begin
    $monitor($time, " a=%d, b=%d, sub=%b, z=%d, Cout=%b, ",a,b,sub,z,Cout);
  end
  
  initial
  begin
    $dumpvars(1, RCA8_testbench);
    #0  sub=0; a=8'h00; b=8'h00; // at time = 0ns
    repeat (31)
    begin
      #50 a <= a + 2; b <= b + 1;
    end
    
    #50 sub=1; a=8'h00; b=8'h00;
    
    repeat (31)
    begin
      #50 a <= a + 2; b <= b + 1;
    end
  end
  
endmodule

RCA8.vcd
$date
	Wed Apr 13 13:49:30 2022
$end
$version
	Icarus Verilog
$end
$timescale
	1ns
$end
$scope module RCA8_testbench $end
$var wire 8 ! z [7:0] $end
$var wire 1 " Cout $end
$var reg 8 # a [7:0] $end
$var reg 8 $ b [7:0] $end
$var reg 1 % sub $end
$upscope $end
$enddefinitions $end
#0
$dumpvars
0%
b0 $
b0 #
0"
b0 !
$end
#500
b11 !
b1 $
b10 #
#1000
b110 !
b10 $
b100 #
#1500
b1001 !
b11 $
b110 #
#2000
b1100 !
b100 $
b1000 #
#2500
b1111 !
b101 $
b1010 #
#3000
b10010 !
b110 $
b1100 #
#3500
b10101 !
b111 $
b1110 #
#4000
b11000 !
b1000 $
b10000 #
#4500
b11011 !
b1001 $
b10010 #
#5000
b11110 !
b1010 $
b10100 #
#5500
b100001 !
b1011 $
b10110 #
#6000
b100100 !
b1100 $
b11000 #
#6500
b100111 !
b1101 $
b11010 #
#7000
b101010 !
b1110 $
b11100 #
#7500
b101101 !
b1111 $
b11110 #
#8000
b110000 !
b10000 $
b100000 #
#8500
b110011 !
b10001 $
b100010 #
#9000
b110110 !
b10010 $
b100100 #
#9500
b111001 !
b10011 $
b100110 #
#10000
b111100 !
b10100 $
b101000 #
#10500
b111111 !
b10101 $
b101010 #
#11000
b1000010 !
b10110 $
b101100 #
#11500
b1000101 !
b10111 $
b101110 #
#12000
b1001000 !
b11000 $
b110000 #
#12500
b1001011 !
b11001 $
b110010 #
#13000
b1001110 !
b11010 $
b110100 #
#13500
b1010001 !
b11011 $
b110110 #
#14000
b1010100 !
b11100 $
b111000 #
#14500
b1010111 !
b11101 $
b111010 #
#15000
b1011010 !
b11110 $
b111100 #
#15500
b1011101 !
b11111 $
b111110 #
#16000
1"
b0 !
b0 $
b0 #
1%
#16500
b1 !
b1 $
b10 #
#17000
b10 !
b10 $
b100 #
#17500
b11 !
b11 $
b110 #
#18000
b100 !
b100 $
b1000 #
#18500
b101 !
b101 $
b1010 #
#19000
b110 !
b110 $
b1100 #
#19500
b111 !
b111 $
b1110 #
#20000
b1000 !
b1000 $
b10000 #
#20500
b1001 !
b1001 $
b10010 #
#21000
b1010 !
b1010 $
b10100 #
#21500
b1011 !
b1011 $
b10110 #
#22000
b1100 !
b1100 $
b11000 #
#22500
b1101 !
b1101 $
b11010 #
#23000
b1110 !
b1110 $
b11100 #
#23500
b1111 !
b1111 $
b11110 #
#24000
b10000 !
b10000 $
b100000 #
#24500
b10001 !
b10001 $
b100010 #
#25000
b10010 !
b10010 $
b100100 #
#25500
b10011 !
b10011 $
b100110 #
#26000
b10100 !
b10100 $
b101000 #
#26500
b10101 !
b10101 $
b101010 #
#27000
b10110 !
b10110 $
b101100 #
#27500
b10111 !
b10111 $
b101110 #
#28000
b11000 !
b11000 $
b110000 #
#28500
b11001 !
b11001 $
b110010 #
#29000
b11010 !
b11010 $
b110100 #
#29500
b11011 !
b11011 $
b110110 #
#30000
b11100 !
b11100 $
b111000 #
#30500
b11101 !
b11101 $
b111010 #
#31000
b11110 !
b11110 $
b111100 #
#31500
b11111 !
b11111 $
b111110 #
